setup.py
ecolor/__init__.py
ecolor/ecolor.py
ecolor.egg-info/PKG-INFO
ecolor.egg-info/SOURCES.txt
ecolor.egg-info/dependency_links.txt
ecolor.egg-info/top_level.txt