Metadata-Version: 1.1
Name: ecolor
Version: 1.0.0
Summary: 打印颜色
Home-page: UNKNOWN
Author: 王哈哈
Author-email: mail65656@163.com
License: UNKNOWN
Platform: UNKNOWN
Classifier: Programming Language :: Python :: 3
Classifier: License :: OSI Approved :: MIT License
Classifier: Operating System :: OS Independent
